django_quantity_field-1.0.1.dist-info/DESCRIPTION.rst
django_quantity_field-1.0.1.dist-info/METADATA
django_quantity_field-1.0.1.dist-info/RECORD
django_quantity_field-1.0.1.dist-info/WHEEL
django_quantity_field-1.0.1.dist-info/metadata.json
django_quantity_field-1.0.1.dist-info/top_level.txt
quantity_field/__init__.py
quantity_field/base.py
quantity_field/fields.py
quantity_field/forms.py
quantity_field/widgets.py
