Metadata-Version: 2.0
Name: django-quantity-field
Version: 1.0.1
Summary: Field for Django models that stores multidimensional physical quantities
Home-page: https://github.com/catcombo/django-quantity-field
Author: Evgeniy Krysanov
Author-email: evgeniy.krysanov@gmail.com
License: MIT
Keywords: django multiple quantity field
Platform: UNKNOWN
Classifier: Development Status :: 5 - Production/Stable
Classifier: Intended Audience :: Developers
Classifier: Environment :: Web Environment
Classifier: Framework :: Django
Classifier: Framework :: Django :: 1.8
Classifier: Framework :: Django :: 1.9
Classifier: Framework :: Django :: 1.10
Classifier: Framework :: Django :: 1.11
Classifier: License :: OSI Approved :: MIT License
Classifier: Operating System :: OS Independent
Classifier: Programming Language :: Python
Classifier: Programming Language :: Python :: 2.7
Classifier: Topic :: Internet :: WWW/HTTP
Classifier: Topic :: Internet :: WWW/HTTP :: Dynamic Content
Requires-Dist: Pint
